Verilog/EXP11/Shifter.v
module Shifter (
	input 			[31:0]	dataa,
	input 			[31:0] 	datab,
	input 					l_or_r,
	input 					a_or_h,
	output 	reg 	[31:0] 	result
);

always @(*) begin
	casex ({a_or_h, l_or_r})
		2'bx0: begin
			result = dataa << datab[4:0];
		end
		2'b01: begin
			result = dataa >>> datab[4:0];
		end
		2'b11: begin
			result = dataa >> datab[4:0];
		end
		default: begin
			result = 32'bx;
		end	
	endcase
end

endmodule //Shifter

Verilog/EXP11/Test/shifter_test.v
`timescale 10ns/10ns

`include "../Shifter.v"

module shifter_test;
    
    reg     [31:0]  a, b;
    wire    [31:0]  c;
    reg             l_or_r, a_or_h;
    Shifter shifter(
        .dataa(a),
        .datab(b),
        .l_or_r(l_or_r),
        .a_or_h(a_or_h),
        .result(c)
    );

    initial begin
        $display("start a test for Module Shifter.");   // 打印开始标记
        $dumpfile("shifter_wave.vcd");                  // 指定记录模拟波形的文件
        $dumpvars(0, shifter_test);                     // 指定记录的模块层级
        #6000 $finish;                                  // 6000个单位时间后结束模拟
    end

    always begin
        a <= -8;
        b <= 2;
        l_or_r <= 0;
        a_or_h <= 0;
        #20;

        l_or_r <= 1;
        a_or_h <= 0;
        #20;

        l_or_r <= 0;
        a_or_h <= 1;
        #20;

        l_or_r <= 1;
        a_or_h <= 1;
        #20;
    end

endmodule //clock_pulse

Verilog/EXP11/Test/shifter_wave.vcd
$date
	Mon Nov 15 10:19:02 2021
$end
$version
	Icarus Verilog
$end
$timescale
	10ns
$end
$scope module shifter_test $end
$var wire 32 ! c [31:0] $end
$var reg 32 " a [31:0] $end
$var reg 1 # a_or_h $end
$var reg 32 $ b [31:0] $end
$var reg 1 % l_or_r $end
$scope module shifter $end
$var wire 1 # a_or_h $end
$var wire 32 & dataa [31:0] $end
$var wire 32 ' datab [31:0] $end
$var wire 1 % l_or_r $end
$var reg 32 ( result [31:0] $end
$upscope $end
$upscope $end
$enddefinitions $end
#0
$dumpvars
b11111111111111111111111111100000 (
b10 '
b11111111111111111111111111111000 &
0%
b10 $
0#
b11111111111111111111111111111000 "
b11111111111111111111111111100000 !
$end
#20
b11111111111111111111111111111110 !
b11111111111111111111111111111110 (
1%
#40
b11111111111111111111111111100000 !
b11111111111111111111111111100000 (
1#
0%
#60
b111111111111111111111111111110 !
b111111111111111111111111111110 (
1%
#80
b11111111111111111111111111100000 !
b11111111111111111111111111100000 (
0#
0%
#100
b11111111111111111111111111111110 !
b11111111111111111111111111111110 (
1%
#120
b11111111111111111111111111100000 !
b11111111111111111111111111100000 (
1#
0%
#140
b111111111111111111111111111110 !
b111111111111111111111111111110 (
1%
#160
b11111111111111111111111111100000 !
b11111111111111111111111111100000 (
0#
0%
#180
b11111111111111111111111111111110 !
b11111111111111111111111111111110 (
1%
#200
b11111111111111111111111111100000 !
b11111111111111111111111111100000 (
1#
0%
#220
b111111111111111111111111111110 !
b111111111111111111111111111110 (
1%
#240
b11111111111111111111111111100000 !
b11111111111111111111111111100000 (
0#
0%
#260
b11111111111111111111111111111110 !
b11111111111111111111111111111110 (
1%
#280
b11111111111111111111111111100000 !
b11111111111111111111111111100000 (
1#
0%
#300
b111111111111111111111111111110 !
b111111111111111111111111111110 (
1%
#320
b11111111111111111111111111100000 !
b11111111111111111111111111100000 (
0#
0%
#340
b11111111111111111111111111111110 !
b11111111111111111111111111111110 (
1%
#360
b11111111111111111111111111100000 !
b11111111111111111111111111100000 (
1#
0%
#380
b111111111111111111111111111110 !
b111111111111111111111111111110 (
1%
#400
b11111111111111111111111111100000 !
b11111111111111111111111111100000 (
0#
0%
#420
b11111111111111111111111111111110 !
b11111111111111111111111111111110 (
1%
#440
b11111111111111111111111111100000 !
b11111111111111111111111111100000 (
1#
0%
#460
b111111111111111111111111111110 !
b111111111111111111111111111110 (
1%
#480
b11111111111111111111111111100000 !
b11111111111111111111111111100000 (
0#
0%
#500
b11111111111111111111111111111110 !
b11111111111111111111111111111110 (
1%
#520
b11111111111111111111111111100000 !
b11111111111111111111111111100000 (
1#
0%
#540
b111111111111111111111111111110 !
b111111111111111111111111111110 (
1%
#560
b11111111111111111111111111100000 !
b11111111111111111111111111100000 (
0#
0%
#580
b11111111111111111111111111111110 !
b11111111111111111111111111111110 (
1%
#600
b11111111111111111111111111100000 !
b11111111111111111111111111100000 (
1#
0%
#620
b111111111111111111111111111110 !
b111111111111111111111111111110 (
1%
#640
b11111111111111111111111111100000 !
b11111111111111111111111111100000 (
0#
0%
#660
b11111111111111111111111111111110 !
b11111111111111111111111111111110 (
1%
#680
b11111111111111111111111111100000 !
b11111111111111111111111111100000 (
1#
0%
#700
b111111111111111111111111111110 !
b111111111111111111111111111110 (
1%
#720
b11111111111111111111111111100000 !
b11111111111111111111111111100000 (
0#
0%
#740
b11111111111111111111111111111110 !
b11111111111111111111111111111110 (
1%
#760
b11111111111111111111111111100000 !
b11111111111111111111111111100000 (
1#
0%
#780
b111111111111111111111111111110 !
b111111111111111111111111111110 (
1%
#800
b11111111111111111111111111100000 !
b11111111111111111111111111100000 (
0#
0%
#820
b11111111111111111111111111111110 !
b11111111111111111111111111111110 (
1%
#840
b11111111111111111111111111100000 !
b11111111111111111111111111100000 (
1#
0%
#860
b111111111111111111111111111110 !
b111111111111111111111111111110 (
1%
#880
b11111111111111111111111111100000 !
b11111111111111111111111111100000 (
0#
0%
#900
b11111111111111111111111111111110 !
b11111111111111111111111111111110 (
1%
#920
b11111111111111111111111111100000 !
b11111111111111111111111111100000 (
1#
0%
#940
b111111111111111111111111111110 !
b111111111111111111111111111110 (
1%
#960
b11111111111111111111111111100000 !
b11111111111111111111111111100000 (
0#
0%
#980
b11111111111111111111111111111110 !
b11111111111111111111111111111110 (
1%
#1000
b11111111111111111111111111100000 !
b11111111111111111111111111100000 (
1#
0%
#1020
b111111111111111111111111111110 !
b111111111111111111111111111110 (
1%
#1040
b11111111111111111111111111100000 !
b11111111111111111111111111100000 (
0#
0%
#1060
b11111111111111111111111111111110 !
b11111111111111111111111111111110 (
1%
#1080
b11111111111111111111111111100000 !
b11111111111111111111111111100000 (
1#
0%
#1100
b111111111111111111111111111110 !
b111111111111111111111111111110 (
1%
#1120
b11111111111111111111111111100000 !
b11111111111111111111111111100000 (
0#
0%
#1140
b11111111111111111111111111111110 !
b11111111111111111111111111111110 (
1%
#1160
b11111111111111111111111111100000 !
b11111111111111111111111111100000 (
1#
0%
#1180
b111111111111111111111111111110 !
b111111111111111111111111111110 (
1%
#1200
b11111111111111111111111111100000 !
b11111111111111111111111111100000 (
0#
0%
#1220
b11111111111111111111111111111110 !
b11111111111111111111111111111110 (
1%
#1240
b11111111111111111111111111100000 !
b11111111111111111111111111100000 (
1#
0%
#1260
b111111111111111111111111111110 !
b111111111111111111111111111110 (
1%
#1280
b11111111111111111111111111100000 !
b11111111111111111111111111100000 (
0#
0%
#1300
b11111111111111111111111111111110 !
b11111111111111111111111111111110 (
1%
#1320
b11111111111111111111111111100000 !
b11111111111111111111111111100000 (
1#
0%
#1340
b111111111111111111111111111110 !
b111111111111111111111111111110 (
1%
#1360
b11111111111111111111111111100000 !
b11111111111111111111111111100000 (
0#
0%
#1380
b11111111111111111111111111111110 !
b11111111111111111111111111111110 (
1%
#1400
b11111111111111111111111111100000 !
b11111111111111111111111111100000 (
1#
0%
#1420
b111111111111111111111111111110 !
b111111111111111111111111111110 (
1%
#1440
b11111111111111111111111111100000 !
b11111111111111111111111111100000 (
0#
0%
#1460
b11111111111111111111111111111110 !
b11111111111111111111111111111110 (
1%
#1480
b11111111111111111111111111100000 !
b11111111111111111111111111100000 (
1#
0%
#1500
b111111111111111111111111111110 !
b111111111111111111111111111110 (
1%
#1520
b11111111111111111111111111100000 !
b11111111111111111111111111100000 (
0#
0%
#1540
b11111111111111111111111111111110 !
b11111111111111111111111111111110 (
1%
#1560
b11111111111111111111111111100000 !
b11111111111111111111111111100000 (
1#
0%
#1580
b111111111111111111111111111110 !
b111111111111111111111111111110 (
1%
#1600
b11111111111111111111111111100000 !
b11111111111111111111111111100000 (
0#
0%
#1620
b11111111111111111111111111111110 !
b11111111111111111111111111111110 (
1%
#1640
b11111111111111111111111111100000 !
b11111111111111111111111111100000 (
1#
0%
#1660
b111111111111111111111111111110 !
b111111111111111111111111111110 (
1%
#1680
b11111111111111111111111111100000 !
b11111111111111111111111111100000 (
0#
0%
#1700
b11111111111111111111111111111110 !
b11111111111111111111111111111110 (
1%
#1720
b11111111111111111111111111100000 !
b11111111111111111111111111100000 (
1#
0%
#1740
b111111111111111111111111111110 !
b111111111111111111111111111110 (
1%
#1760
b11111111111111111111111111100000 !
b11111111111111111111111111100000 (
0#
0%
#1780
b11111111111111111111111111111110 !
b11111111111111111111111111111110 (
1%
#1800
b11111111111111111111111111100000 !
b11111111111111111111111111100000 (
1#
0%
#1820
b111111111111111111111111111110 !
b111111111111111111111111111110 (
1%
#1840
b11111111111111111111111111100000 !
b11111111111111111111111111100000 (
0#
0%
#1860
b11111111111111111111111111111110 !
b11111111111111111111111111111110 (
1%
#1880
b11111111111111111111111111100000 !
b11111111111111111111111111100000 (
1#
0%
#1900
b111111111111111111111111111110 !
b111111111111111111111111111110 (
1%
#1920
b11111111111111111111111111100000 !
b11111111111111111111111111100000 (
0#
0%
#1940
b11111111111111111111111111111110 !
b11111111111111111111111111111110 (
1%
#1960
b11111111111111111111111111100000 !
b11111111111111111111111111100000 (
1#
0%
#1980
b111111111111111111111111111110 !
b111111111111111111111111111110 (
1%
#2000
b11111111111111111111111111100000 !
b11111111111111111111111111100000 (
0#
0%
#2020
b11111111111111111111111111111110 !
b11111111111111111111111111111110 (
1%
#2040
b11111111111111111111111111100000 !
b11111111111111111111111111100000 (
1#
0%
#2060
b111111111111111111111111111110 !
b111111111111111111111111111110 (
1%
#2080
b11111111111111111111111111100000 !
b11111111111111111111111111100000 (
0#
0%
#2100
b11111111111111111111111111111110 !
b11111111111111111111111111111110 (
1%
#2120
b11111111111111111111111111100000 !
b11111111111111111111111111100000 (
1#
0%
#2140
b111111111111111111111111111110 !
b111111111111111111111111111110 (
1%
#2160
b11111111111111111111111111100000 !
b11111111111111111111111111100000 (
0#
0%
#2180
b11111111111111111111111111111110 !
b11111111111111111111111111111110 (
1%
#2200
b11111111111111111111111111100000 !
b11111111111111111111111111100000 (
1#
0%
#2220
b111111111111111111111111111110 !
b111111111111111111111111111110 (
1%
#2240
b11111111111111111111111111100000 !
b11111111111111111111111111100000 (
0#
0%
#2260
b11111111111111111111111111111110 !
b11111111111111111111111111111110 (
1%
#2280
b11111111111111111111111111100000 !
b11111111111111111111111111100000 (
1#
0%
#2300
b111111111111111111111111111110 !
b111111111111111111111111111110 (
1%
#2320
b11111111111111111111111111100000 !
b11111111111111111111111111100000 (
0#
0%
#2340
b11111111111111111111111111111110 !
b11111111111111111111111111111110 (
1%
#2360
b11111111111111111111111111100000 !
b11111111111111111111111111100000 (
1#
0%
#2380
b111111111111111111111111111110 !
b111111111111111111111111111110 (
1%
#2400
b11111111111111111111111111100000 !
b11111111111111111111111111100000 (
0#
0%
#2420
b11111111111111111111111111111110 !
b11111111111111111111111111111110 (
1%
#2440
b11111111111111111111111111100000 !
b11111111111111111111111111100000 (
1#
0%
#2460
b111111111111111111111111111110 !
b111111111111111111111111111110 (
1%
#2480
b11111111111111111111111111100000 !
b11111111111111111111111111100000 (
0#
0%
#2500
b11111111111111111111111111111110 !
b11111111111111111111111111111110 (
1%
#2520
b11111111111111111111111111100000 !
b11111111111111111111111111100000 (
1#
0%
#2540
b111111111111111111111111111110 !
b111111111111111111111111111110 (
1%
#2560
b11111111111111111111111111100000 !
b11111111111111111111111111100000 (
0#
0%
#2580
b11111111111111111111111111111110 !
b11111111111111111111111111111110 (
1%
#2600
b11111111111111111111111111100000 !
b11111111111111111111111111100000 (
1#
0%
#2620
b111111111111111111111111111110 !
b111111111111111111111111111110 (
1%
#2640
b11111111111111111111111111100000 !
b11111111111111111111111111100000 (
0#
0%
#2660
b11111111111111111111111111111110 !
b11111111111111111111111111111110 (
1%
#2680
b11111111111111111111111111100000 !
b11111111111111111111111111100000 (
1#
0%
#2700
b111111111111111111111111111110 !
b111111111111111111111111111110 (
1%
#2720
b11111111111111111111111111100000 !
b11111111111111111111111111100000 (
0#
0%
#2740
b11111111111111111111111111111110 !
b11111111111111111111111111111110 (
1%
#2760
b11111111111111111111111111100000 !
b11111111111111111111111111100000 (
1#
0%
#2780
b111111111111111111111111111110 !
b111111111111111111111111111110 (
1%
#2800
b11111111111111111111111111100000 !
b11111111111111111111111111100000 (
0#
0%
#2820
b11111111111111111111111111111110 !
b11111111111111111111111111111110 (
1%
#2840
b11111111111111111111111111100000 !
b11111111111111111111111111100000 (
1#
0%
#2860
b111111111111111111111111111110 !
b111111111111111111111111111110 (
1%
#2880
b11111111111111111111111111100000 !
b11111111111111111111111111100000 (
0#
0%
#2900
b11111111111111111111111111111110 !
b11111111111111111111111111111110 (
1%
#2920
b11111111111111111111111111100000 !
b11111111111111111111111111100000 (
1#
0%
#2940
b111111111111111111111111111110 !
b111111111111111111111111111110 (
1%
#2960
b11111111111111111111111111100000 !
b11111111111111111111111111100000 (
0#
0%
#2980
b11111111111111111111111111111110 !
b11111111111111111111111111111110 (
1%
#3000
b11111111111111111111111111100000 !
b11111111111111111111111111100000 (
1#
0%
#3020
b111111111111111111111111111110 !
b111111111111111111111111111110 (
1%
#3040
b11111111111111111111111111100000 !
b11111111111111111111111111100000 (
0#
0%
#3060
b11111111111111111111111111111110 !
b11111111111111111111111111111110 (
1%
#3080
b11111111111111111111111111100000 !
b11111111111111111111111111100000 (
1#
0%
#3100
b111111111111111111111111111110 !
b111111111111111111111111111110 (
1%
#3120
b11111111111111111111111111100000 !
b11111111111111111111111111100000 (
0#
0%
#3140
b11111111111111111111111111111110 !
b11111111111111111111111111111110 (
1%
#3160
b11111111111111111111111111100000 !
b11111111111111111111111111100000 (
1#
0%
#3180
b111111111111111111111111111110 !
b111111111111111111111111111110 (
1%
#3200
b11111111111111111111111111100000 !
b11111111111111111111111111100000 (
0#
0%
#3220
b11111111111111111111111111111110 !
b11111111111111111111111111111110 (
1%
#3240
b11111111111111111111111111100000 !
b11111111111111111111111111100000 (
1#
0%
#3260
b111111111111111111111111111110 !
b111111111111111111111111111110 (
1%
#3280
b11111111111111111111111111100000 !
b11111111111111111111111111100000 (
0#
0%
#3300
b11111111111111111111111111111110 !
b11111111111111111111111111111110 (
1%
#3320
b11111111111111111111111111100000 !
b11111111111111111111111111100000 (
1#
0%
#3340
b111111111111111111111111111110 !
b111111111111111111111111111110 (
1%
#3360
b11111111111111111111111111100000 !
b11111111111111111111111111100000 (
0#
0%
#3380
b11111111111111111111111111111110 !
b11111111111111111111111111111110 (
1%
#3400
b11111111111111111111111111100000 !
b11111111111111111111111111100000 (
1#
0%
#3420
b111111111111111111111111111110 !
b111111111111111111111111111110 (
1%
#3440
b11111111111111111111111111100000 !
b11111111111111111111111111100000 (
0#
0%
#3460
b11111111111111111111111111111110 !
b11111111111111111111111111111110 (
1%
#3480
b11111111111111111111111111100000 !
b11111111111111111111111111100000 (
1#
0%
#3500
b111111111111111111111111111110 !
b111111111111111111111111111110 (
1%
#3520
b11111111111111111111111111100000 !
b11111111111111111111111111100000 (
0#
0%
#3540
b11111111111111111111111111111110 !
b11111111111111111111111111111110 (
1%
#3560
b11111111111111111111111111100000 !
b11111111111111111111111111100000 (
1#
0%
#3580
b111111111111111111111111111110 !
b111111111111111111111111111110 (
1%
#3600
b11111111111111111111111111100000 !
b11111111111111111111111111100000 (
0#
0%
#3620
b11111111111111111111111111111110 !
b11111111111111111111111111111110 (
1%
#3640
b11111111111111111111111111100000 !
b11111111111111111111111111100000 (
1#
0%
#3660
b111111111111111111111111111110 !
b111111111111111111111111111110 (
1%
#3680
b11111111111111111111111111100000 !
b11111111111111111111111111100000 (
0#
0%
#3700
b11111111111111111111111111111110 !
b11111111111111111111111111111110 (
1%
#3720
b11111111111111111111111111100000 !
b11111111111111111111111111100000 (
1#
0%
#3740
b111111111111111111111111111110 !
b111111111111111111111111111110 (
1%
#3760
b11111111111111111111111111100000 !
b11111111111111111111111111100000 (
0#
0%
#3780
b11111111111111111111111111111110 !
b11111111111111111111111111111110 (
1%
#3800
b11111111111111111111111111100000 !
b11111111111111111111111111100000 (
1#
0%
#3820
b111111111111111111111111111110 !
b111111111111111111111111111110 (
1%
#3840
b11111111111111111111111111100000 !
b11111111111111111111111111100000 (
0#
0%
#3860
b11111111111111111111111111111110 !
b11111111111111111111111111111110 (
1%
#3880
b11111111111111111111111111100000 !
b11111111111111111111111111100000 (
1#
0%
#3900
b111111111111111111111111111110 !
b111111111111111111111111111110 (
1%
#3920
b11111111111111111111111111100000 !
b11111111111111111111111111100000 (
0#
0%
#3940
b11111111111111111111111111111110 !
b11111111111111111111111111111110 (
1%
#3960
b11111111111111111111111111100000 !
b11111111111111111111111111100000 (
1#
0%
#3980
b111111111111111111111111111110 !
b111111111111111111111111111110 (
1%
#4000
b11111111111111111111111111100000 !
b11111111111111111111111111100000 (
0#
0%
#4020
b11111111111111111111111111111110 !
b11111111111111111111111111111110 (
1%
#4040
b11111111111111111111111111100000 !
b11111111111111111111111111100000 (
1#
0%
#4060
b111111111111111111111111111110 !
b111111111111111111111111111110 (
1%
#4080
b11111111111111111111111111100000 !
b11111111111111111111111111100000 (
0#
0%
#4100
b11111111111111111111111111111110 !
b11111111111111111111111111111110 (
1%
#4120
b11111111111111111111111111100000 !
b11111111111111111111111111100000 (
1#
0%
#4140
b111111111111111111111111111110 !
b111111111111111111111111111110 (
1%
#4160
b11111111111111111111111111100000 !
b11111111111111111111111111100000 (
0#
0%
#4180
b11111111111111111111111111111110 !
b11111111111111111111111111111110 (
1%
#4200
b11111111111111111111111111100000 !
b11111111111111111111111111100000 (
1#
0%
#4220
b111111111111111111111111111110 !
b111111111111111111111111111110 (
1%
#4240
b11111111111111111111111111100000 !
b11111111111111111111111111100000 (
0#
0%
#4260
b11111111111111111111111111111110 !
b11111111111111111111111111111110 (
1%
#4280
b11111111111111111111111111100000 !
b11111111111111111111111111100000 (
1#
0%
#4300
b111111111111111111111111111110 !
b111111111111111111111111111110 (
1%
#4320
b11111111111111111111111111100000 !
b11111111111111111111111111100000 (
0#
0%
#4340
b11111111111111111111111111111110 !
b11111111111111111111111111111110 (
1%
#4360
b11111111111111111111111111100000 !
b11111111111111111111111111100000 (
1#
0%
#4380
b111111111111111111111111111110 !
b111111111111111111111111111110 (
1%
#4400
b11111111111111111111111111100000 !
b11111111111111111111111111100000 (
0#
0%
#4420
b11111111111111111111111111111110 !
b11111111111111111111111111111110 (
1%
#4440
b11111111111111111111111111100000 !
b11111111111111111111111111100000 (
1#
0%
#4460
b111111111111111111111111111110 !
b111111111111111111111111111110 (
1%
#4480
b11111111111111111111111111100000 !
b11111111111111111111111111100000 (
0#
0%
#4500
b11111111111111111111111111111110 !
b11111111111111111111111111111110 (
1%
#4520
b11111111111111111111111111100000 !
b11111111111111111111111111100000 (
1#
0%
#4540
b111111111111111111111111111110 !
b111111111111111111111111111110 (
1%
#4560
b11111111111111111111111111100000 !
b11111111111111111111111111100000 (
0#
0%
#4580
b11111111111111111111111111111110 !
b11111111111111111111111111111110 (
1%
#4600
b11111111111111111111111111100000 !
b11111111111111111111111111100000 (
1#
0%
#4620
b111111111111111111111111111110 !
b111111111111111111111111111110 (
1%
#4640
b11111111111111111111111111100000 !
b11111111111111111111111111100000 (
0#
0%
#4660
b11111111111111111111111111111110 !
b11111111111111111111111111111110 (
1%
#4680
b11111111111111111111111111100000 !
b11111111111111111111111111100000 (
1#
0%
#4700
b111111111111111111111111111110 !
b111111111111111111111111111110 (
1%
#4720
b11111111111111111111111111100000 !
b11111111111111111111111111100000 (
0#
0%
#4740
b11111111111111111111111111111110 !
b11111111111111111111111111111110 (
1%
#4760
b11111111111111111111111111100000 !
b11111111111111111111111111100000 (
1#
0%
#4780
b111111111111111111111111111110 !
b111111111111111111111111111110 (
1%
#4800
b11111111111111111111111111100000 !
b11111111111111111111111111100000 (
0#
0%
#4820
b11111111111111111111111111111110 !
b11111111111111111111111111111110 (
1%
#4840
b11111111111111111111111111100000 !
b11111111111111111111111111100000 (
1#
0%
#4860
b111111111111111111111111111110 !
b111111111111111111111111111110 (
1%
#4880
b11111111111111111111111111100000 !
b11111111111111111111111111100000 (
0#
0%
#4900
b11111111111111111111111111111110 !
b11111111111111111111111111111110 (
1%
#4920
b11111111111111111111111111100000 !
b11111111111111111111111111100000 (
1#
0%
#4940
b111111111111111111111111111110 !
b111111111111111111111111111110 (
1%
#4960
b11111111111111111111111111100000 !
b11111111111111111111111111100000 (
0#
0%
#4980
b11111111111111111111111111111110 !
b11111111111111111111111111111110 (
1%
#5000
b11111111111111111111111111100000 !
b11111111111111111111111111100000 (
1#
0%
#5020
b111111111111111111111111111110 !
b111111111111111111111111111110 (
1%
#5040
b11111111111111111111111111100000 !
b11111111111111111111111111100000 (
0#
0%
#5060
b11111111111111111111111111111110 !
b11111111111111111111111111111110 (
1%
#5080
b11111111111111111111111111100000 !
b11111111111111111111111111100000 (
1#
0%
#5100
b111111111111111111111111111110 !
b111111111111111111111111111110 (
1%
#5120
b11111111111111111111111111100000 !
b11111111111111111111111111100000 (
0#
0%
#5140
b11111111111111111111111111111110 !
b11111111111111111111111111111110 (
1%
#5160
b11111111111111111111111111100000 !
b11111111111111111111111111100000 (
1#
0%
#5180
b111111111111111111111111111110 !
b111111111111111111111111111110 (
1%
#5200
b11111111111111111111111111100000 !
b11111111111111111111111111100000 (
0#
0%
#5220
b11111111111111111111111111111110 !
b11111111111111111111111111111110 (
1%
#5240
b11111111111111111111111111100000 !
b11111111111111111111111111100000 (
1#
0%
#5260
b111111111111111111111111111110 !
b111111111111111111111111111110 (
1%
#5280
b11111111111111111111111111100000 !
b11111111111111111111111111100000 (
0#
0%
#5300
b11111111111111111111111111111110 !
b11111111111111111111111111111110 (
1%
#5320
b11111111111111111111111111100000 !
b11111111111111111111111111100000 (
1#
0%
#5340
b111111111111111111111111111110 !
b111111111111111111111111111110 (
1%
#5360
b11111111111111111111111111100000 !
b11111111111111111111111111100000 (
0#
0%
#5380
b11111111111111111111111111111110 !
b11111111111111111111111111111110 (
1%
#5400
b11111111111111111111111111100000 !
b11111111111111111111111111100000 (
1#
0%
#5420
b111111111111111111111111111110 !
b111111111111111111111111111110 (
1%
#5440
b11111111111111111111111111100000 !
b11111111111111111111111111100000 (
0#
0%
#5460
b11111111111111111111111111111110 !
b11111111111111111111111111111110 (
1%
#5480
b11111111111111111111111111100000 !
b11111111111111111111111111100000 (
1#
0%
#5500
b111111111111111111111111111110 !
b111111111111111111111111111110 (
1%
#5520
b11111111111111111111111111100000 !
b11111111111111111111111111100000 (
0#
0%
#5540
b11111111111111111111111111111110 !
b11111111111111111111111111111110 (
1%
#5560
b11111111111111111111111111100000 !
b11111111111111111111111111100000 (
1#
0%
#5580
b111111111111111111111111111110 !
b111111111111111111111111111110 (
1%
#5600
b11111111111111111111111111100000 !
b11111111111111111111111111100000 (
0#
0%
#5620
b11111111111111111111111111111110 !
b11111111111111111111111111111110 (
1%
#5640
b11111111111111111111111111100000 !
b11111111111111111111111111100000 (
1#
0%
#5660
b111111111111111111111111111110 !
b111111111111111111111111111110 (
1%
#5680
b11111111111111111111111111100000 !
b11111111111111111111111111100000 (
0#
0%
#5700
b11111111111111111111111111111110 !
b11111111111111111111111111111110 (
1%
#5720
b11111111111111111111111111100000 !
b11111111111111111111111111100000 (
1#
0%
#5740
b111111111111111111111111111110 !
b111111111111111111111111111110 (
1%
#5760
b11111111111111111111111111100000 !
b11111111111111111111111111100000 (
0#
0%
#5780
b11111111111111111111111111111110 !
b11111111111111111111111111111110 (
1%
#5800
b11111111111111111111111111100000 !
b11111111111111111111111111100000 (
1#
0%
#5820
b111111111111111111111111111110 !
b111111111111111111111111111110 (
1%
#5840
b11111111111111111111111111100000 !
b11111111111111111111111111100000 (
0#
0%
#5860
b11111111111111111111111111111110 !
b11111111111111111111111111111110 (
1%
#5880
b11111111111111111111111111100000 !
b11111111111111111111111111100000 (
1#
0%
#5900
b111111111111111111111111111110 !
b111111111111111111111111111110 (
1%
#5920
b11111111111111111111111111100000 !
b11111111111111111111111111100000 (
0#
0%
#5940
b11111111111111111111111111111110 !
b11111111111111111111111111111110 (
1%
#5960
b11111111111111111111111111100000 !
b11111111111111111111111111100000 (
1#
0%
#5980
b111111111111111111111111111110 !
b111111111111111111111111111110 (
1%
#6000
b11111111111111111111111111100000 !
b11111111111111111111111111100000 (
0#
0%
